h5ffmpeg/anm.py
h5ffmpeg/anm_legacy.py
h5ffmpeg/constants.py
h5ffmpeg/ffmpeg_filter.py
h5ffmpeg/gpu_utils.py
h5ffmpeg/patches.py
h5ffmpeg/utils.py
h5ffmpeg/_ffmpeg_filter.c
h5ffmpeg/_ffmpeg_filter.cp312-win_amd64.pyd
h5ffmpeg/_version.py
h5ffmpeg/__init__.py
h5ffmpeg-2.3.2.dist-info/DELVEWHEEL
h5ffmpeg-2.3.2.dist-info/METADATA
h5ffmpeg-2.3.2.dist-info/RECORD
h5ffmpeg-2.3.2.dist-info/top_level.txt
h5ffmpeg-2.3.2.dist-info/WHEEL
h5ffmpeg-2.3.2.dist-info/licenses/LICENSE
h5ffmpeg.libs/avcodec-61-4adf65ff8628dc369a0ce08006d59690.dll
h5ffmpeg.libs/avutil-59-2e6cd0a65a892c3af3d0cc1b6588e2ed.dll
h5ffmpeg.libs/hdf5-4d215edfa26ee69766075d60ebdb8e09.dll
h5ffmpeg.libs/swresample-5-bc8f02363b82bd0df5a76ea43ff1341f.dll
h5ffmpeg.libs/swscale-8-82ab4ab7727215457590a523bba34291.dll
