Metadata-Version: 2.4
Name: h5ffmpeg
Version: 2.3.2
Summary: HDF5 filter plugin for FFMPEG video codec compression
Home-page: https://github.com/Cai-Lab-at-University-of-Michigan/ffmpeg_HDF5_filter
Author: Bin Duan@Cailab, University of Michigan
Author-email: duanb@umich.edu
License: MIT
Classifier: Development Status :: 4 - Beta
Classifier: Intended Audience :: Science/Research
Classifier: Programming Language :: Python :: 3
Classifier: Programming Language :: Python :: 3.10
Classifier: Programming Language :: Python :: 3.11
Classifier: Programming Language :: Python :: 3.12
Classifier: Programming Language :: Python :: 3.13
Classifier: Topic :: Scientific/Engineering
Classifier: Topic :: Scientific/Engineering :: Bio-Informatics
Classifier: Topic :: Scientific/Engineering :: Image Processing
Classifier: Topic :: Multimedia :: Video :: Conversion
Requires-Python: >=3.10,<4.0
License-File: LICENSE
Requires-Dist: h5py>=3.8.0
Requires-Dist: numpy>=1.15.0
Requires-Dist: colorama>=0.4.6
Requires-Dist: tabulate>=0.9.0
Requires-Dist: matplotlib>=3.10.3
Requires-Dist: scikit-image>=0.25.2
Provides-Extra: nvidia
Requires-Dist: cupy-cuda11x; extra == "nvidia"
Provides-Extra: intel
Requires-Dist: intel-openmp; extra == "intel"
Dynamic: author
Dynamic: author-email
Dynamic: classifier
Dynamic: description
Dynamic: description-content-type
Dynamic: home-page
Dynamic: license
Dynamic: license-file
Dynamic: provides-extra
Dynamic: requires-dist
Dynamic: requires-python
Dynamic: summary
